{
  "Senior Python Developer (DS направление)": [
    [
      null,
      null,
      null
    ],
    "https://hh.ru/vacancy/39312484?query=python"
  ],
  "Специалист по машинному обучению (Python, Machine learning)": [
    [
      null,
      150000,
      "руб"
    ],
    "https://hh.ru/vacancy/39815662?query=python"
  ],
  "Разработчик Asterisk / Python": [
    [
      null,
      null,
      null
    ],
    "https://hh.ru/vacancy/39472611?query=python"
  ],
  "Senior Software Development Engineer in Test (Python)": [
    [
      null,
      null,
      null
    ],
    "https://hh.ru/vacancy/39494550?query=python"
  ],
  "Программист Python": [
    [
      120000,
      170000,
      "руб"
    ],
    "https://hh.ru/vacancy/39602570?query=python"
  ],
  "Разработчик Python": [
    [
      70000,
      null,
      "руб"
    ],
    "https://hh.ru/vacancy/39849346?query=python"
  ],
  "Backend разработчик на python": [
    [
      80000,
      null,
      "руб"
    ],
    "https://hh.ru/vacancy/39153243?query=python"
  ],
  "Python разработчик": [
    [
      null,
      null,
      null
    ],
    "https://hh.ru/vacancy/39782469?query=python"
  ],
  "Python developer": [
    [
      220000,
      null,
      "руб"
    ],
    "https://hh.ru/vacancy/39618651?query=python"
  ],
  "Senior Python developer": [
    [
      4000,
      null,
      "usd"
    ],
    "https://hh.ru/vacancy/30005963?query=python"
  ],
  "Senior Python Backend Developer (Machine Learning)": [
    [
      250000,
      null,
      "руб"
    ],
    "https://hh.ru/vacancy/39388485?query=python"
  ],
  "Разработчик C++/Python": [
    [
      60000,
      90000,
      "руб"
    ],
    "https://hh.ru/vacancy/39738913?query=python"
  ],
  "Python-разработчик (Django, DRF)": [
    [
      60000,
      150000,
      "руб"
    ],
    "https://hh.ru/vacancy/39736489?query=python"
  ],
  "Data Scientist / Machine Learning Engineer": [
    [
      150000,
      null,
      "руб"
    ],
    "https://hh.ru/vacancy/39538528?query=python"
  ],
  "BackEnd-разработчик (Python)": [
    [
      null,
      null,
      null
    ],
    "https://hh.ru/vacancy/39272567?query=python"
  ],
  "Старший разработчик Python": [
    [
      200000,
      250000,
      "руб"
    ],
    "https://hh.ru/vacancy/39388712?query=python"
  ],
  "Data Scientist": [
    [
      120000,
      170000,
      "руб"
    ],
    "https://hh.ru/vacancy/39602668?query=python"
  ],
  "Python-Разработчик (удаленно)": [
    [
      null,
      250000,
      "руб"
    ],
    "https://hh.ru/vacancy/39415818?query=python"
  ],
  "Разработчик на Go/Python": [
    [
      150000,
      null,
      "руб"
    ],
    "https://hh.ru/vacancy/39791019?query=python"
  ],
  "Python разработчик (Django)": [
    [
      100000,
      150000,
      "руб"
    ],
    "https://hh.ru/vacancy/39844911?query=python"
  ],
  "Senior backend developer (C++\\Python)": [
    [
      270000,
      320000,
      "руб"
    ],
    "https://hh.ru/vacancy/39264973?query=python"
  ],
  "Senior Python Backend Developer": [
    [
      250000,
      null,
      "руб"
    ],
    "https://hh.ru/vacancy/39730720?query=python"
  ],
  "Разработчик автоматических тестов GUI (Python, Squish)": [
    [
      3000,
      null,
      "usd"
    ],
    "https://hh.ru/vacancy/38036578?query=python"
  ],
  "Middle Разработчик Python / Django удалённо": [
    [
      60000,
      140000,
      "руб"
    ],
    "https://hh.ru/vacancy/39769884?query=python"
  ],
  "Golang/Python разработчик": [
    [
      70000,
      120000,
      "руб"
    ],
    "https://hh.ru/vacancy/39860865?query=python"
  ],
  "Разработчик на Python": [
    [
      null,
      null,
      null
    ],
    "https://hh.ru/vacancy/39297364?query=python"
  ],
  "Python Developer": [
    [
      null,
      null,
      null
    ],
    "https://hh.ru/vacancy/39701802?query=python"
  ],
  "QA Automation Engineer (Python)": [
    [
      120000,
      null,
      "руб"
    ],
    "https://hh.ru/vacancy/39068627?query=python"
  ],
  "Teamlead Backend (Python)": [
    [
      100000,
      160000,
      "руб"
    ],
    "https://hh.ru/vacancy/39635096?query=python"
  ],
  "Backend python/Django разработчик": [
    [
      120000,
      200000,
      "руб"
    ],
    "https://hh.ru/vacancy/39779033?query=python"
  ],
  "Разработчик на Python (Full stack)": [
    [
      180000,
      null,
      "руб"
    ],
    "https://hh.ru/vacancy/39349530?query=python"
  ],
  "Python-разработчик в Марусю": [
    [
      null,
      null,
      null
    ],
    "https://hh.ru/vacancy/38514489?query=python"
  ],
  "Python middle developer": [
    [
      120000,
      160000,
      "руб"
    ],
    "https://hh.ru/vacancy/36449432?query=python"
  ],
  "Backend-разработчик Python": [
    [
      140000,
      160000,
      "руб"
    ],
    "https://hh.ru/vacancy/39679111?query=python"
  ],
  "Программист Python, VUE, React, C++": [
    [
      70000,
      150000,
      "руб"
    ],
    "https://hh.ru/vacancy/39799002?query=python"
  ],
  "Python / Django Mid Developer": [
    [
      90000,
      130000,
      "руб"
    ],
    "https://hh.ru/vacancy/39595700?query=python"
  ]
}